ghmarkdown/__init__.py
ghmarkdown/ghmarkdown.py
ghmarkdown/html.dat
ghmarkdown-2.0.2.dist-info/DESCRIPTION.rst
ghmarkdown-2.0.2.dist-info/METADATA
ghmarkdown-2.0.2.dist-info/RECORD
ghmarkdown-2.0.2.dist-info/WHEEL
ghmarkdown-2.0.2.dist-info/entry_points.txt
ghmarkdown-2.0.2.dist-info/metadata.json
ghmarkdown-2.0.2.dist-info/top_level.txt
