Metadata-Version: 2.0
Name: ghmarkdown
Version: 2.0.2
Summary: ghmarkdown is the complete command-line             tool for GitHub-flavored markdown
Home-page: http://github.com/lucasem/ghmarkdown
Author: Lucas Morales
Author-email: lucas@lucasem.com
License: GNU GPL v2.0
Keywords: markdown live html github command command-line cli
Platform: UNKNOWN
Classifier: Intended Audience :: Developers
Classifier: Topic :: Communications
Classifier: Topic :: Software Development
Classifier: Topic :: Software Development :: Documentation
Classifier: Topic :: Text Processing :: Markup
Classifier: Topic :: Text Processing :: Markup :: HTML
Classifier: License :: OSI Approved :: GNU General Public License v2 (GPLv2)
Classifier: Programming Language :: Python :: 3
Classifier: Programming Language :: Python :: 3.2
Classifier: Programming Language :: Python :: 3.3
Classifier: Programming Language :: Python :: 3.4
Classifier: Programming Language :: Python :: 3.5
Classifier: Programming Language :: Python :: 3.6
Requires-Python: >=3
Requires-Dist: requests
